odoo8_addon_l10n_br_hr-8.0.0.0.0.99.dev12-py2.7-nspkg.pth
odoo8_addon_l10n_br_hr-8.0.0.0.0.99.dev12.dist-info/METADATA
odoo8_addon_l10n_br_hr-8.0.0.0.0.99.dev12.dist-info/RECORD
odoo8_addon_l10n_br_hr-8.0.0.0.0.99.dev12.dist-info/WHEEL
odoo8_addon_l10n_br_hr-8.0.0.0.0.99.dev12.dist-info/namespace_packages.txt
odoo8_addon_l10n_br_hr-8.0.0.0.0.99.dev12.dist-info/top_level.txt
odoo_addons/l10n_br_hr/README.rst
odoo_addons/l10n_br_hr/__init__.py
odoo_addons/l10n_br_hr/__openerp__.py
odoo_addons/l10n_br_hr/data/dependent_type_data.xml
odoo_addons/l10n_br_hr/data/hr_employee_data.xml
odoo_addons/l10n_br_hr/data/hr_employee_nationality_code_data.xml
odoo_addons/l10n_br_hr/data/l10n_br_hr.cbo.csv
odoo_addons/l10n_br_hr/i18n/pt_BR.po
odoo_addons/l10n_br_hr/model/__init__.py
odoo_addons/l10n_br_hr/model/hr_employee.py
odoo_addons/l10n_br_hr/model/hr_job.py
odoo_addons/l10n_br_hr/model/l10n_br_hr.py
odoo_addons/l10n_br_hr/model/res_company.py
odoo_addons/l10n_br_hr/security/ir.model.access.csv
odoo_addons/l10n_br_hr/static/description/icon.png
odoo_addons/l10n_br_hr/test/l10n_br_hr_demo.yml
odoo_addons/l10n_br_hr/view/hr_employee_view.xml
odoo_addons/l10n_br_hr/view/hr_job_view.xml
odoo_addons/l10n_br_hr/view/l10n_br_hr_cbo_view.xml
odoo_addons/l10n_br_hr/view/res_company_view.xml
