Metadata-Version: 2.1
Name: odoo8-addon-l10n-br-hr
Version: 8.0.0.0.0.99.dev12
Summary: Brazilian Localization HR
Home-page: http://www.kmee.com.br
Author: KMEE, Odoo Community Association (OCA)
Author-email: support@odoo-community.org
License: AGPL-3
Platform: UNKNOWN
Classifier: Programming Language :: Python
Classifier: Framework :: Odoo
Classifier: License :: OSI Approved :: GNU Affero General Public License v3
Requires-Python: ~=2.7
Requires-Dist: odoo8-addon-l10n-br-base
Requires-Dist: odoo (<9.0a,>=8.0a)
